youtubetaggenerator/test.py
youtubetaggenerator/youtubetaggenerator.py
youtubetaggenerator-2.0.0.dist-info/LICENSE
youtubetaggenerator-2.0.0.dist-info/METADATA
youtubetaggenerator-2.0.0.dist-info/WHEEL
youtubetaggenerator-2.0.0.dist-info/top_level.txt
youtubetaggenerator-2.0.0.dist-info/RECORD
