Metadata-Version: 2.1
Name: youtubetaggenerator
Version: 2.0.0
Summary: This Library allows Developers to get Youtube Tag nased on youtube title adding this tags in video will boost the views of videos 
Home-page: https://github.com/soumilshah1995/AppleStock
Author: Soumil Nitin Shah
Author-email: soushah@my.bridgeport.edu
License: MIT
Platform: UNKNOWN
Classifier: License :: OSI Approved :: MIT License
Classifier: Programming Language :: Python :: 3
Classifier: Programming Language :: Python :: 3.7
Requires-Dist: requests
